cycleosm/__init__.py
cycleosm/bikeosm.py
cycleosm/pbfdownloader.py
cycleosm/utils.py
cycleosm/static/general - states.csv
cycleosm/static/geofabrik - Sept2024.csv
cycleosm/static/geofabrik - latest.csv
cycleosm/static/geofabrik - test.csv
cycleosm/static/osm_links - cycleways.txt
cycleosm/static/osm_links - fclasses.txt
cycleosm/static/osm_links - not_bikelanes.txt
cycleosm/static/osm_links - tags.csv
cycleosm-0.0.2.4.dist-info/METADATA
cycleosm-0.0.2.4.dist-info/WHEEL
cycleosm-0.0.2.4.dist-info/licenses/LICENSE
cycleosm-0.0.2.4.dist-info/RECORD
